searchdata/SearchdataBingSearch.py
searchdata/SearchdataGoogleAutocomplete.py
searchdata/SearchdataGoogleEvents.py
searchdata/SearchdataGoogleJobs.py
searchdata/SearchdataGoogleJobsListing.py
searchdata/SearchdataGoogleMaps.py
searchdata/SearchdataGoogleMapsReviews.py
searchdata/SearchdataGoogleProduct.py
searchdata/SearchdataGoogleReverseImage.py
searchdata/SearchdataGoogleScholar.py
searchdata/SearchdataGoogleScholarAuthor.py
searchdata/SearchdataGoogleScholarCite.py
searchdata/SearchdataGoogleScholarProfiles.py
searchdata/SearchdataGoogleSearch.py
searchdata/SearchdataLocations.py
searchdata/SearchdataSDK.py
searchdata/SearchdataYandexSearch.py
searchdata/__init__.py
searchdata-1.0.1.dist-info/LICENSE.txt
searchdata-1.0.1.dist-info/METADATA
searchdata-1.0.1.dist-info/WHEEL
searchdata-1.0.1.dist-info/top_level.txt
searchdata-1.0.1.dist-info/RECORD
