Metadata-Version: 2.1
Name: searchdata
Version: 1.0.1
Summary: Searchdata Python SDK
Home-page: https://github.com/SearchDataAPI/python-sdk
Author: Sorin-Gabriel Marica
Author-email: sorin.marica@jeco.dev
Maintainer: searchdata
Maintainer-email: account@jeco.dev
License: MIT
Platform: UNKNOWN
Classifier: License :: OSI Approved :: MIT License
Classifier: Programming Language :: Python
Classifier: Programming Language :: Python :: 3
Classifier: Programming Language :: Python :: 3.6
Classifier: Programming Language :: Python :: 3.7
Classifier: Programming Language :: Python :: 3.8
Classifier: Topic :: Software Development :: Libraries :: Python Modules
Requires-Python: >=3.6
License-File: LICENSE.txt
Requires-Dist: requests
